<?xml version="1.0" encoding="UTF-8"?>
<ContratoEmpleo xmlns:xsi="http://www.w3.org/2001/XMLSchema-instance" xsi:noNamespaceSchemaLocation="ContratoEmpleo.xsd">
    <Empleado idMesa="2" idZona="0">
        <NombreE>Juan Gomez</NombreE>
        <PuestoTrabajo>Camarero/a</PuestoTrabajo>
        <Salario>1300</Salario>
        <Telefono>+34658669933</Telefono>
        <Sector>Restaurante</Sector>
    </Empleado>
    <Empleado idMesa="5" idZona="0">
        <NombreE>Benat Ezquerro</NombreE>
        <PuestoTrabajo>Cocinero/a</PuestoTrabajo>
        <Salario>2000</Salario>
        <Telefono>+34689541235</Telefono>
        <Sector>Restaurante</Sector>
    </Empleado>
    <Empleado idMesa="2" idZona="0">
        <NombreE>Juan Gomez</NombreE>
        <PuestoTrabajo>Camarero/a</PuestoTrabajo>
        <Salario>1300</Salario>
        <Telefono>+34658669933</Telefono>
        <Sector>Gimnasio</Sector>
    </Empleado>
    <Empleado idMesa="2" idZona="0">
        <NombreE>Juan Gomez</NombreE>
        <PuestoTrabajo>Camarero/a</PuestoTrabajo>
        <Salario>1300</Salario>
        <Telefono>+34658669933</Telefono>
        <Sector>Gimnasio</Sector>
    </Empleado>
    <Empleado idMesa="2" idZona="0">
        <NombreE>Juan Gomez</NombreE>
        <PuestoTrabajo>Camarero/a</PuestoTrabajo>
        <Salario>1300</Salario>
        <Telefono>+34658669933</Telefono>
        <Sector>Gimnasio</Sector>
    </Empleado>
    <Empleado idMesa="2" idZona="0">
        <NombreE>Juan Gomez</NombreE>
        <PuestoTrabajo>Camarero/a</PuestoTrabajo>
        <Salario>1300</Salario>
        <Telefono>+34658669933</Telefono>
        <Sector>Gimnasio</Sector>
    </Empleado>
    <Empleado idMesa="2" idZona="0">
        <NombreE>Juan Gomez</NombreE>
        <PuestoTrabajo>Camarero/a</PuestoTrabajo>
        <Salario>1300</Salario>
        <Telefono>+34658669933</Telefono>
        <Sector>Gimnasio</Sector>
    </Empleado>
    <Empleado idMesa="2" idZona="0">
        <NombreE>Juan Gomez</NombreE>
        <PuestoTrabajo>Camarero/a</PuestoTrabajo>
        <Salario>1300</Salario>
        <Telefono>+34658669933</Telefono>
        <Sector>Gimnasio</Sector>
    </Empleado>
    <Empleado idMesa="2" idZona="0">
        <NombreE>Juan Gomez</NombreE>
        <PuestoTrabajo>Camarero/a</PuestoTrabajo>
        <Salario>1300</Salario>
        <Telefono>+34658669933</Telefono>
        <Sector>Gimnasio</Sector>
    </Empleado>
    <Empleado idMesa="2" idZona="0">
        <NombreE>Juan Gomez</NombreE>
        <PuestoTrabajo>Camarero/a</PuestoTrabajo>
        <Salario>1300</Salario>
        <Telefono>+34658669933</Telefono>
        <Sector>Gimnasio</Sector>
    </Empleado>
</ContratoEmpleo>